{
  "updated_at": "2026-06-27T13:52:34.318Z",
  "source": "card text normalization",
  "changes": {
    "fire_001": [
      "攻撃範囲を前方1マスのみに変更",
      "効果文を前方1マス表記に更新",
      "Sheet-based stat pass: increased HP from 3 to 4."
    ],
    "fire_002": [
      "後方を攻撃範囲から除外",
      "後方を弱点に追加"
    ],
    "fire_003": [
      "攻撃/反撃範囲を前後に変更",
      "弱点を左右に変更",
      "効果対象をコスト2以下に制限",
      "対象クリーチャーを墓地から除外する文言に変更"
    ],
    "fire_005": [
      "攻撃方式を範囲から1体選択に変更",
      "効果文に選択攻撃を追記"
    ],
    "fire_009": [
      "ATKを2に変更",
      "連撃付与対象を攻撃範囲が1体のみのクリーチャーに変更",
      "連撃の説明を効果文に追記"
    ],
    "fire_014": [
      "ATKを3に変更"
    ],
    "fire_016": [
      "重ね召喚の説明を効果文に追記"
    ],
    "fire_ace_001": [
      "スペル使用時にダメージ+1、マナ+1、1ドローする効果文に変更",
      "Balance: changed attack range to front/left/right choice 1 while keeping physical attack."
    ],
    "fire_ace_002": [
      "攻撃範囲に左右を追加",
      "効果文に前左右3マス同時攻撃を追記"
    ],
    "water_001": [
      "起動効果から召喚時効果に変更",
      "コストをマナ1のみの表記に変更",
      "空きマスを空いているマスに統一"
    ],
    "water_005": [
      "ATKを2に変更",
      "デッキトップをデッキの上からに統一",
      "Balance: reduced HP from 3 to 2 for 3-cost magic attacker.",
      "Magic attacker weakness normalized to all adjacent directions except front: rear/left/right."
    ],
    "water_008": [
      "ATKを2に変更",
      "被攻撃クリーチャーの再行動不可/効果無効化に効果文を変更",
      "Magic attacker weakness normalized to all adjacent directions except front: rear/left/right."
    ],
    "water_010": [
      "ATKを2に変更",
      "攻撃範囲を前方2マスに変更",
      "攻撃方式を同時攻撃に変更",
      "効果文に前方2マス同時攻撃を追記",
      "守護の弱点なしカードに背後弱点(-1,0)を追加",
      "Defense range normalization: counter range matched to attack range."
    ],
    "water_012": [
      "ATKを2に変更",
      "攻撃/反撃範囲を前方2マスに変更",
      "攻撃方式を範囲から1体選択に変更",
      "移動/向き変更の誘発対象を自分または相手に変更",
      "ターン制限を削除"
    ],
    "water_013": [
      "弱点をなしに変更",
      "移動/向き変更の誘発対象を自分または相手に変更"
    ],
    "water_014": [
      "相手クリーチャーの移動/向き変更で自身ATK+1する効果文に変更"
    ],
    "water_015": [
      "ATKを2に変更",
      "ターン制限を削除",
      "Magic attacker weakness normalized to all adjacent directions except front: rear/left/right."
    ],
    "water_016": [
      "ATKを4に変更",
      "攻撃/反撃範囲を前方2マスに変更",
      "弱点を後方に変更",
      "攻撃方式を範囲から1体選択に変更",
      "場のクリーチャーを3体まで敵味方問わず向き変更できる効果文に変更"
    ],
    "water_017": [
      "移動/向き変更時にマナを得る効果文に変更"
    ],
    "water_ace_001": [
      "ATKを4に変更",
      "任意のクリーチャーをデッキから加えられる効果文に変更"
    ],
    "earth_004": [
      "ATKを2に変更",
      "再行動コストを2に変更",
      "移動を強制、向き変更自由の効果文に変更",
      "空きマスを空いているマスに統一"
    ],
    "earth_008": [
      "墓地の対象クリーチャーを除外する効果文に変更",
      "Magic attacker weakness normalized to all adjacent directions except front: rear/left/right."
    ],
    "earth_009": [
      "攻撃/反撃範囲を前方2マスに変更",
      "弱点を後方に変更",
      "攻撃方式を範囲から1体選択に変更"
    ],
    "earth_010": [
      "Sheet-based stat pass: increased HP from 3 to 4."
    ],
    "earth_011": [
      "攻撃時の再行動コストが1になる効果文に変更"
    ],
    "earth_012": [
      "コストを1に変更",
      "再行動コストを2に変更",
      "影の徒党員のATKを2から1に変更",
      "影の徒党員を2マナ / HP2 / ATK1に変更"
    ],
    "earth_ace_002": [
      "ATKを3に変更",
      "攻撃範囲を全方向に変更",
      "攻撃方式を範囲から1体選択に変更",
      "『先制と不屈を持つ』の重複説明を効果文から削除",
      "守護者の攻撃を物理・周囲4マス・範囲から1体選択に変更",
      "守護の弱点なしカードに背後弱点(-1,0)を追加"
    ],
    "earth_017": [
      "HPを5に変更",
      "ATKを2に変更",
      "守護の弱点なしカードに背後弱点(-1,0)を追加",
      "Defense range normalization: counter range matched to attack range."
    ],
    "wood_002": [
      "HPを2に変更",
      "ATKを3に変更",
      "再行動コストを1に変更",
      "VP?3???",
      "Magic attacker weakness normalized to all adjacent directions except front: rear/left/right."
    ],
    "wood_003": [
      "ATKを2に変更",
      "隣接クリーチャーの攻撃力を+1する常在効果文に変更"
    ],
    "wood_004": [
      "ATKを2に変更",
      "攻撃/反撃範囲を前後に変更",
      "弱点を左右に変更",
      "隣接する自陣クリーチャー数に応じてATK+1する効果文に変更"
    ],
    "wood_007": [
      "ATKを2に変更",
      "前後左右を弱点に変更",
      "Magic attacker weakness normalized to all adjacent directions except front: rear/left/right."
    ],
    "wood_008": [
      "右側を弱点に追加",
      "通常のボーナスに加える文言へ効果文を修正"
    ],
    "fire_010": [
      "レビューでは反撃確認のみ。現状値を維持",
      "このターンをこのターン中に統一",
      "Sheet-based stat pass: increased HP from 2 to 3."
    ],
    "fire_011": [
      "Sheet-based stat pass: increased HP from 2 to 3."
    ],
    "water_002": [
      "魔道キャラのため反撃範囲なしを維持",
      "ATKは未確定のため共有レビューに保留",
      "Magic attacker weakness normalized to all adjacent directions except front: rear/left/right."
    ],
    "water_006": [
      "魔道キャラのため反撃範囲なしを維持",
      "Magic attacker weakness normalized to all adjacent directions except front: rear/left/right."
    ],
    "wood_010": [
      "VPを2に変更",
      "ATKを2に変更",
      "攻撃/反撃範囲を前方1マスに変更",
      "弱点を後方に変更",
      "次の相手ターンを次の相手のターン中に統一"
    ],
    "wood_011": [
      "ATKを3に変更",
      "VPを4に変更",
      "すべてのクリーチャーの体力+1の常在効果文に変更",
      "Magic attacker weakness normalized to all adjacent directions except front: rear/left/right."
    ],
    "wood_012": [
      "ATKを2に変更",
      "Balance: changed to HP3/ATK1 and added rear weakness for 4-target attack."
    ],
    "wood_013": [
      "体力加算効果を削除",
      "ステータス変動ターンは再行動コスト0になる効果文に変更"
    ],
    "neutral_001": [
      "HPを4に変更",
      "ATKを3に変更",
      "相手が発動した向き変更・移動効果を受けない効果文に変更"
    ],
    "neutral_003": [
      "HPを3に変更",
      "VPを3に変更",
      "攻撃/反撃範囲を前方2マスに変更",
      "攻撃方式を同時攻撃に変更",
      "前方2マスの召喚コスト/再行動コスト+2の効果文に変更",
      "守護の弱点なしカードに背後弱点(-1,0)を追加"
    ],
    "neutral_004": [
      "HPを3に変更",
      "VPを2に変更",
      "ATKを1に変更"
    ],
    "neutral_008": [
      "HPを4に変更",
      "ATKを3に変更",
      "魔道攻撃に変更",
      "魔道キャラのため反撃範囲なしに変更",
      "守護の弱点なしカードに背後弱点(-1,0)を追加",
      "Balance: changed to HP3/ATK2 for 4-cost magic defense unit.",
      "Magic attacker weakness normalized to all adjacent directions except front: rear/left/right."
    ],
    "neutral_010": [
      "HPを4に変更",
      "ATKを2に変更"
    ],
    "neutral_011": [
      "コストを4に変更",
      "ATKを4に変更"
    ],
    "neutral_012": [
      "コストを3に変更",
      "ATKを2に変更",
      "相手クリーチャー1体の召喚時効果を発動できる効果文に変更"
    ],
    "neutral_013": [
      "HPを2に変更",
      "左右を弱点に追加",
      "魔道攻撃を受けない効果文に変更"
    ],
    "earth_013": [
      "再行動コストを1に変更"
    ],
    "earth_014": [
      "????1???",
      "C1 balance: reduced HP from 2 to 1 because it keeps a light summon effect."
    ],
    "wood_015": [
      "撃破時の攻撃力上昇を次のターンのみ+2に変更"
    ],
    "neutral_014": [
      "守護の弱点なしカードに背後弱点(-1,0)を追加",
      "Balance: reduced ATK from 2 to 1 for 2-cost defense unit.",
      "Defense range normalization: counter range matched to attack range."
    ],
    "wood_017": [
      "????1???",
      "挑発キーワードを追加し、召喚時およびターン開始時の挙動を効果文に明記",
      "C1 balance: removed Taunt keyword and effect."
    ],
    "neutral_015": [
      "????????????"
    ],
    "wood_018": [
      "HPを5に変更",
      "ATKを4に変更",
      "移動・退却耐性を削除",
      "守護の弱点なしカードに背後弱点(-1,0)を追加",
      "Defense range normalization: counter range matched to attack range."
    ],
    "water_021": [
      "VP?2????ATK??????????",
      "ATKを攻撃力に統一"
    ],
    "neutral_016": [
      "ATKを0に変更",
      "攻撃範囲を前方2マスに変更",
      "攻撃方式を前方2マスへの貫通攻撃想定に変更",
      "ATKを攻撃力に統一"
    ],
    "water_022": [
      "ドロー効果のターン制限を削除"
    ],
    "draw_001": [
      "知略(draw)陣営削除に伴いマスターから除外"
    ],
    "draw_002": [
      "知略(draw)陣営削除に伴いマスターから除外"
    ],
    "draw_003": [
      "知略(draw)陣営削除に伴いマスターから除外"
    ],
    "draw_004": [
      "知略(draw)陣営削除に伴いマスターから除外"
    ],
    "draw_005": [
      "知略(draw)陣営削除に伴いマスターから除外"
    ],
    "draw_006": [
      "知略(draw)陣営削除に伴いマスターから除外"
    ],
    "draw_007": [
      "知略(draw)陣営削除に伴いマスターから除外"
    ],
    "draw_008": [
      "知略(draw)陣営削除に伴いマスターから除外"
    ],
    "draw_009": [
      "知略(draw)陣営削除に伴いマスターから除外"
    ],
    "draw_010": [
      "知略(draw)陣営削除に伴いマスターから除外"
    ],
    "spell_water_002": [
      "知略(draw)陣営削除に伴いマスターから除外"
    ],
    "spell_water_006": [
      "知略(draw)陣営削除に伴いマスターから除外"
    ],
    "spell_water_007": [
      "知略(draw)陣営削除に伴いマスターから除外"
    ],
    "spell_neutral_004": [
      "知略(draw)陣営削除に伴いマスターから除外"
    ],
    "spell_neutral_005": [
      "知略(draw)陣営削除に伴いマスターから除外"
    ],
    "spell_neutral_008": [
      "知略(draw)陣営削除に伴いマスターから除外"
    ],
    "ult_draw_001": [
      "知略(draw)陣営削除に伴いマスターから除外"
    ],
    "spell_fire_001": [
      "コストを1に変更",
      "自軍を自分のに統一",
      "このターンをこのターン中に統一"
    ],
    "spell_fire_002": [
      "コストを0に変更",
      "このターンをこのターン中に統一"
    ],
    "spell_fire_007": [
      "レビュー指定によりマスターから削除"
    ],
    "spell_water_004": [
      "コストを1に変更",
      "次の相手ターンを次の相手のターン中に統一"
    ],
    "spell_water_005": [
      "レビュー指定によりマスターから削除"
    ],
    "spell_earth_001": [
      "コストを1に変更",
      "自軍を自分のに統一",
      "このターンをこのターン中に統一"
    ],
    "spell_earth_002": [
      "コストを1に変更",
      "自軍を自分のに統一"
    ],
    "spell_earth_003": [
      "効果に手札1枚を捨てる代償を追加"
    ],
    "spell_earth_004": [
      "魔道攻撃を対象外とする記述を追加",
      "自軍を自分のに統一"
    ],
    "spell_earth_007": [
      "コストを4に変更",
      "召喚されたクリーチャーはこのターン攻撃できない記述を追加",
      "このターンをこのターン中に統一",
      "コスト無料をコストを支払わずに統一",
      "空きマスを空いているマスに統一"
    ],
    "spell_wood_002": [
      "コストを1に変更",
      "対象を2体に変更"
    ],
    "spell_neutral_001": [
      "カードを1枚引く効果を追加"
    ],
    "spell_neutral_007": [
      "魔道攻撃を行うクリーチャーを対象外とする記述を追加"
    ],
    "spell_water_011": [
      "コストを2に変更",
      "効果期間を次のターン終了時までに変更"
    ],
    "spell_earth_011": [
      "コストを2に変更",
      "スペル削減調整により「再臨の儀」を削除"
    ],
    "spell_fire_008": [
      "コストを1に変更"
    ],
    "spell_water_012": [
      "召喚時効果の発動回数を2回に変更"
    ],
    "spell_earth_012": [
      "レビュー指定によりマスターから削除"
    ],
    "spell_water_013": [
      "レビュー指定によりマスターから削除"
    ],
    "spell_neutral_009": [
      "レビュー指定によりマスターから削除"
    ],
    "fire_015": [
      "空きマスを空いているマスに統一"
    ],
    "water_020": [
      "デッキトップをデッキの上からに統一"
    ],
    "wood_016": [
      "空きマスを空いているマスに統一"
    ],
    "spell_fire_004": [
      "このターンをこのターン中に統一"
    ],
    "spell_fire_005": [
      "自軍を自分のに統一"
    ],
    "spell_water_001": [
      "空きマスを空いているマスに統一"
    ],
    "spell_earth_005": [
      "自軍を自分のに統一"
    ],
    "spell_neutral_006": [
      "このターンをこのターン中に統一",
      "コスト無料をコストを支払わずに統一",
      "空きマスを空いているマスに統一"
    ],
    "spell_water_014": [
      "空きマスを空いているマスに統一"
    ],
    "ult_spell_001": [
      "このターンをこのターン中に統一",
      "発動条件を「相手の場にクリーチャーが3体以上いる」に変更"
    ],
    "ult_aggro_001": [
      "このターンをこのターン中に統一",
      "発動条件を「相手の場にクリーチャーが3体以上いる」に変更"
    ],
    "ult_cip_001": [
      "このターンをこのターン中に統一",
      "発動条件を「相手の場にクリーチャーが3体以上いる」に変更"
    ],
    "ult_defense_001": [
      "コスト無料をコストを支払わずに統一",
      "空きマスを空いているマスに統一",
      "発動条件を「相手の場にクリーチャーが3体以上いる」に変更"
    ],
    "ult_meta_001": [
      "発動条件を「相手の場にクリーチャーが3体以上いる」に変更"
    ],
    "water_009": [
      "Balance: reduced HP from 2 to 1 for 2-cost magic attacker.",
      "Magic attacker weakness normalized to all adjacent directions except front: rear/left/right."
    ],
    "water_004": [
      "Magic attacker weakness normalized to all adjacent directions except front: rear/left/right."
    ],
    "earth_ace_001": [
      "Magic attacker weakness normalized to all adjacent directions except front: rear/left/right."
    ],
    "wood_009": [
      "Magic attacker weakness normalized to all adjacent directions except front: rear/left/right."
    ]
  },
  "global_changes": [
    "attack_type が魔道のキャラクター13枚は、反撃範囲をすべてなしに変更",
    "知略(draw)陣営を削除し、所属キャラクター10枚・アイテム6枚・ウルト1枚をマスターから除外",
    "効果文の表記ゆれを一部統一: 27件",
    "4陣営の再行動コストを、ATK基準とシートの再行動マナ基準を土台に、複数対象・魔道・攻撃誘発で補正する方針へ調整"
  ]
}
